Metadata-Version: 2.1
Name: disnake-ext-menus
Version: 0.0.2
Summary: An extension module to make reaction based menus with disnake
Home-page: https://github.com/Kraots/disnake-ext-menus
Author: Rapptz, Kraots
License: UNKNOWN
Platform: UNKNOWN
Requires-Python: >=3.8.0
